{
  "url": "http://chinashipbuilding.cn/ship.aspx?pklujyukkpp4FgBXcanmkhTk8Pl4EN",
  "ts": 1758645208,
  "sisters": [
    {
      "name": "Hantong",
      "link": "http://chinashipbuilding.cn/ship.aspx?pklujyukkpp4FgbCsanmkhTk8Pl4EN",
      "ship_type": "Bulk Carrier, 210,000 tons",
      "owner_company": "COSCO Shipping Bulk (中远海运散运)",
      "shipyard": "Jiangsu New Hantong HI",
      "date_contract": "2024 - 08"
    },
    {
      "name": "Hantong",
      "link": "http://chinashipbuilding.cn/ship.aspx?pklujyukkpp4FgbScanmkhTk8Pl4EN",
      "ship_type": "Bulk Carrier, 210,000 tons",
      "owner_company": "COSCO Shipping Bulk (中远海运散运)",
      "shipyard": "Jiangsu New Hantong HI",
      "date_contract": "2024 - 08"
    },
    {
      "name": "Hantong",
      "link": "http://chinashipbuilding.cn/ship.aspx?pklujyukkpp4FgBJBanmkhTk8Pl4EN",
      "ship_type": "Bulk Carrier, 210,000 tons",
      "owner_company": "COSCO Shipping Bulk (中远海运散运)",
      "shipyard": "Jiangsu New Hantong HI",
      "date_contract": "2024 - 08"
    },
    {
      "name": "Hantong",
      "link": "http://chinashipbuilding.cn/ship.aspx?pklujyukkpp4FgBSganmkhTk8Pl4EN",
      "ship_type": "Bulk Carrier, 210,000 tons",
      "owner_company": "COSCO Shipping Bulk (中远海运散运)",
      "shipyard": "Jiangsu New Hantong HI",
      "date_contract": "2024 - 08"
    },
    {
      "name": "Hantong",
      "link": "http://chinashipbuilding.cn/ship.aspx?pklujyukkpp4FgBSbanmkhTk8Pl4EN",
      "ship_type": "Bulk Carrier, 210,000 tons",
      "owner_company": "COSCO Shipping Bulk (中远海运散运)",
      "shipyard": "Jiangsu New Hantong HI",
      "date_contract": "2024 - 08"
    },
    {
      "name": "Hantong",
      "link": "http://chinashipbuilding.cn/ship.aspx?pklujyukkpp4FgBSBanmkhTk8Pl4EN",
      "ship_type": "Bulk Carrier, 210,000 tons",
      "owner_company": "COSCO Shipping Bulk (中远海运散运)",
      "shipyard": "Jiangsu New Hantong HI",
      "date_contract": "2024 - 08"
    },
    {
      "name": "Hantong",
      "link": "http://chinashipbuilding.cn/ship.aspx?pklujyukkpp4FgBSCanmkhTk8Pl4EN",
      "ship_type": "Bulk Carrier, 210,000 tons",
      "owner_company": "COSCO Shipping Bulk (中远海运散运)",
      "shipyard": "Jiangsu New Hantong HI",
      "date_contract": "2024 - 08"
    },
    {
      "name": "Jiangsu Hantong HT210-435",
      "link": "http://chinashipbuilding.cn/ship.aspx?pklujyukkpp4cBcbcanmkhTk8Pl4EN",
      "ship_type": "Bulk Carrier, 211,000 tons",
      "owner_company": "Unknown",
      "shipyard": "Jiangsu New Hantong HI",
      "date_contract": "2024 - 12"
    },
    {
      "name": "Hantong Wing HT210-434",
      "link": "http://chinashipbuilding.cn/ship.aspx?pklujyukkpp4cBcbXanmkhTk8Pl4EN",
      "ship_type": "Bulk Carrier, 211,000 tons",
      "owner_company": "Unknown",
      "shipyard": "Jiangsu New Hantong HI",
      "date_contract": "2024 - 12"
    }
  ]
}