{
  "url": "http://chinashipbuilding.cn/ship.aspx?pklujyukkpp4cCXgSanmkhTk8Pl4EN",
  "origin_yard": "CSSC, Huangpu-Wenchong (Changzhou)",
  "ts": 1758716583,
  "sisters": [
    {
      "name": "Huangpu Wenchong H2575",
      "link": "http://chinashipbuilding.cn/ship.aspx?pklujyukkpp4cXcBganmkhTk8Pl4EN",
      "ship_type": "LPG Tanker, 58,800 cbm",
      "owner_company": "Eastern Pacific Shipping",
      "shipyard": "Huangpu-Wenchong Shipbuilding",
      "date_contract": "2024 - 08"
    },
    {
      "name": "Huangpu Wenchong H2574",
      "link": "http://chinashipbuilding.cn/ship.aspx?pklujyukkpp4cXcBJanmkhTk8Pl4EN",
      "ship_type": "LPG Tanker, 58,800 cbm",
      "owner_company": "Eastern Pacific Shipping",
      "shipyard": "Huangpu-Wenchong Shipbuilding",
      "date_contract": "2024 - 08"
    },
    {
      "name": "Huangpu Wenchong H2573",
      "link": "http://chinashipbuilding.cn/ship.aspx?pklujyukkpp4cXcBcanmkhTk8Pl4EN",
      "ship_type": "LPG Tanker, 58,800 cbm",
      "owner_company": "Eastern Pacific Shipping",
      "shipyard": "Huangpu-Wenchong Shipbuilding",
      "date_contract": "2024 - 08"
    },
    {
      "name": "Huangpu Wenchong H2572",
      "link": "http://chinashipbuilding.cn/ship.aspx?pklujyukkpp4cXcBXanmkhTk8Pl4EN",
      "ship_type": "LPG Tanker, 58,800 cbm",
      "owner_company": "Eastern Pacific Shipping",
      "shipyard": "Huangpu-Wenchong Shipbuilding",
      "date_contract": "2024 - 08"
    },
    {
      "name": "Huangpu Wenchong H2570",
      "link": "http://chinashipbuilding.cn/ship.aspx?pklujyukkpp4cCXgsanmkhTk8Pl4EN",
      "ship_type": "LPG Tanker, 41,000 cbm",
      "owner_company": "Wideshine Enterprise (西南海运)",
      "shipyard": "Huangpu-Wenchong Shipbuilding",
      "date_contract": "2024 - 11"
    },
    {
      "name": "Huangpu Wenchong H2569",
      "link": "http://chinashipbuilding.cn/ship.aspx?pklujyukkpp4cCXgCanmkhTk8Pl4EN",
      "ship_type": "LPG Tanker, 41,000 cbm",
      "owner_company": "Wideshine Enterprise (西南海运)",
      "shipyard": "Huangpu-Wenchong Shipbuilding",
      "date_contract": "2024 - 11"
    },
    {
      "name": "Huangpu Wenchong H2568",
      "link": "http://chinashipbuilding.cn/ship.aspx?pklujyukkpp4cCXgbanmkhTk8Pl4EN",
      "ship_type": "LPG Tanker, 41,000 cbm",
      "owner_company": "Wideshine Enterprise (西南海运)",
      "shipyard": "Huangpu-Wenchong Shipbuilding",
      "date_contract": "2024 - 11"
    },
    {
      "name": "Huangpu Wenchong H2535",
      "link": "http://chinashipbuilding.cn/ship.aspx?pklujyukkpp4cCXgBanmkhTk8Pl4EN",
      "ship_type": "LPG Tanker, 25,000 cbm",
      "owner_company": "Wideshine Enterprise (西南海运)",
      "shipyard": "Huangpu-Wenchong Shipbuilding",
      "date_contract": "2024 - 11"
    },
    {
      "name": "Huangpu Wenchong H2534",
      "link": "http://chinashipbuilding.cn/ship.aspx?pklujyukkpp4cCXJganmkhTk8Pl4EN",
      "ship_type": "LPG Tanker, 25,000 cbm",
      "owner_company": "Wideshine Enterprise (西南海运)",
      "shipyard": "Huangpu-Wenchong Shipbuilding",
      "date_contract": "2024 - 11"
    },
    {
      "name": "Huangpu Wenchong H2443",
      "link": "http://chinashipbuilding.cn/ship.aspx?pklujyukkpp4SXXXJanmkhTk8Pl4EN",
      "ship_type": "LPG Tanker, 48,000 cbm",
      "owner_company": "Benelux Overseas Inc.",
      "shipyard": "Huangpu-Wenchong Shipbuilding",
      "date_contract": "2024 - 03"
    }
  ]
}